discoruns/__init__.py
discoruns/main.py
discoruns/mechanism.py
discoruns/artifacts/__init__.py
discoruns/artifacts/windows.yaml
discoruns/artifacts/windows_persistence.yaml
discoruns/mechanisms/__init__.py
discoruns/mechanisms/app_cert_dlls.py
discoruns/mechanisms/app_init_dlls.py
discoruns/mechanisms/application_shimming.py
discoruns/mechanisms/authentication_packages.py
discoruns/mechanisms/browser_extensions.py
discoruns/mechanisms/codecs.py
discoruns/mechanisms/com_hijacking.py
discoruns/mechanisms/file_associations.py
discoruns/mechanisms/image_hijacks.py
discoruns/mechanisms/known_dlls.py
discoruns/mechanisms/logon.py
discoruns/mechanisms/netsh_helper.py
discoruns/mechanisms/office_application_startup.py
discoruns/mechanisms/port_monitors.py
discoruns/mechanisms/powershell_profiles.py
discoruns/mechanisms/run_keys.py
discoruns/mechanisms/scheduled_tasks.py
discoruns/mechanisms/screensaver.py
discoruns/mechanisms/security_support_provider.py
discoruns/mechanisms/services_and_drivers.py
discoruns/mechanisms/sip_and_trust_provider_hijacking.py
discoruns/mechanisms/time_providers.py
discoruns/mechanisms/winlogon_helper.py
discoruns/mechanisms/winsock_providers.py
discoruns/wrapper/__init__.py
discoruns/wrapper/ac_wrapper.py
discoruns/wrapper/fs_wrapper.py
discoruns-0.1.0.dist-info/LICENSE
discoruns-0.1.0.dist-info/METADATA
discoruns-0.1.0.dist-info/WHEEL
discoruns-0.1.0.dist-info/entry_points.txt
discoruns-0.1.0.dist-info/top_level.txt
discoruns-0.1.0.dist-info/RECORD
