Metadata-Version: 2.1
Name: discoruns
Version: 0.1.0
Summary: Python library for windows persistence mechanism extraction
Home-page: https://github.com/korbster/discoruns
Author: Korbinian Karl
License: UNKNOWN
Platform: UNKNOWN
Requires-Dist: forensicstore (<0.18.0,>=0.17.0)
Requires-Dist: tabulate (==0.8.7)
